Metadata-Version: 2.1
Name: opentelemetry-exporter-otlp-proto-grpc-custom
Version: 1.15.0
Summary: OpenTelemetry Collector Protobuf over gRPC Exporter
Project-URL: Homepage, https://github.com/open-telemetry/opentelemetry-python/tree/main/exporter/opentelemetry-exporter-otlp-proto-grpc
Author-email: OpenTelemetry Authors <cncf-opentelemetry-contributors@lists.cncf.io>
License-Expression: Apache-2.0
License-File: LICENSE
Classifier: Development Status :: 5 - Production/Stable
Classifier: Intended Audience :: Developers
Classifier: License :: OSI Approved :: Apache Software License
Classifier: Programming Language :: Python
Classifier: Programming Language :: Python :: 3
Classifier: Programming Language :: Python :: 3.7
Classifier: Programming Language :: Python :: 3.8
Classifier: Programming Language :: Python :: 3.9
Classifier: Programming Language :: Python :: 3.10
Classifier: Programming Language :: Python :: 3.11
Requires-Python: >=3.7
Requires-Dist: backoff<2.0.0,>=1.10.0; python_version < '3.7'
Requires-Dist: backoff<3.0.0,>=1.10.0; python_version >= '3.7'
Requires-Dist: googleapis-common-protos~=1.52
Requires-Dist: grpcio<2.0.0,>=1.0.0
Requires-Dist: opentelemetry-api~=1.12
Requires-Dist: opentelemetry-proto==1.15.0
Requires-Dist: opentelemetry-sdk~=1.12
Provides-Extra: test
Requires-Dist: pytest-grpc; extra == 'test'
